euler/__init__.py
euler/angles.py
euler/convert.py
euler/matrix.py
euler/py.typed
euler/utils.py
neverlocal_euler-1.0.2.dist-info/LICENSE
neverlocal_euler-1.0.2.dist-info/METADATA
neverlocal_euler-1.0.2.dist-info/WHEEL
neverlocal_euler-1.0.2.dist-info/top_level.txt
neverlocal_euler-1.0.2.dist-info/RECORD
