Metadata-Version: 2.2
Name: neverlocal-euler
Version: 1.0.2
Summary: A library for Euler angle computation and conversion.
Author: NeverLocal
Project-URL: Repository, https://github.com/neverlocal/euler
Project-URL: Issues, https://github.com/neverlocal/euler/issues
Classifier: Programming Language :: Python :: 3
Classifier: Operating System :: OS Independent
Classifier: Development Status :: 4 - Beta
Classifier: Programming Language :: Python :: 3.13
Classifier: Programming Language :: Python :: 3.12
Classifier: Programming Language :: Python :: 3.11
Classifier: Programming Language :: Python :: 3.10
Classifier: Natural Language :: English
Classifier: Typing :: Typed
Requires-Python: >=3.10
License-File: LICENSE
Requires-Dist: numpy>=1.23
